CreateEasyVars.py
createeasyvars-1.0.0.dist-info/WHEEL
createeasyvars-1.0.0.dist-info/METADATA
createeasyvars-1.0.0.dist-info/RECORD
