Metadata-Version: 2.1
Name: createeasyvars
Version: 1.0.0
Summary: Welcome to the new library for creating lightweight variables such as: string, int, bool. Creating a variable is very easy!
Author: tikotstudio
Author-email: tikotstudio@yandex.ru
Requires-Python: >=3.7,<4.0
Classifier: Programming Language :: Python :: 3
Classifier: Programming Language :: Python :: 3.7
Classifier: Programming Language :: Python :: 3.8
Classifier: Programming Language :: Python :: 3.9
